create_smithery_python/__init__.py
create_smithery_python/cli.py
create_smithery_python_unofficial-0.1.1.dist-info/METADATA
create_smithery_python_unofficial-0.1.1.dist-info/WHEEL
create_smithery_python_unofficial-0.1.1.dist-info/entry_points.txt
create_smithery_python_unofficial-0.1.1.dist-info/licenses/LICENSE
create_smithery_python_unofficial-0.1.1.dist-info/RECORD
