Metadata-Version: 2.4
Name: create-smithery-python-unofficial
Version: 0.1.1
Summary: Unofficial Python CLI for creating MCP servers for Smithery
Project-URL: Homepage, https://github.com/yourusername/create-smithery-python-unofficial
Project-URL: Issues, https://github.com/yourusername/create-smithery-python-unofficial/issues
Author-email: Your Name <your.email@example.com>
License: MIT
License-File: LICENSE
Keywords: cli,fastmcp,mcp,smithery,unofficial
Classifier: Development Status :: 3 - Alpha
Classifier: Intended Audience :: Developers
Classifier: License :: OSI Approved :: MIT License
Classifier: Programming Language :: Python :: 3
Classifier: Programming Language :: Python :: 3.9
Classifier: Programming Language :: Python :: 3.10
Classifier: Programming Language :: Python :: 3.11
Classifier: Programming Language :: Python :: 3.12
Requires-Python: >=3.9
Requires-Dist: rich>=13.0.0
Requires-Dist: typer>=0.9.0
